forgejo_api/__init__.py
forgejo_api/api_client.py
forgejo_api/configuration.py
forgejo_api/rest.py
forgejo_api/api/__init__.py
forgejo_api/api/activitypub_api.py
forgejo_api/api/admin_api.py
forgejo_api/api/issue_api.py
forgejo_api/api/miscellaneous_api.py
forgejo_api/api/notification_api.py
forgejo_api/api/organization_api.py
forgejo_api/api/package_api.py
forgejo_api/api/repository_api.py
forgejo_api/api/settings_api.py
forgejo_api/api/user_api.py
forgejo_api/models/__init__.py
forgejo_api/models/access_token.py
forgejo_api/models/activity.py
forgejo_api/models/activity_pub.py
forgejo_api/models/add_collaborator_option.py
forgejo_api/models/add_time_option.py
forgejo_api/models/annotated_tag.py
forgejo_api/models/annotated_tag_object.py
forgejo_api/models/api_error.py
forgejo_api/models/attachment.py
forgejo_api/models/blocked_user.py
forgejo_api/models/branch.py
forgejo_api/models/branch_protection.py
forgejo_api/models/change_file_operation.py
forgejo_api/models/change_files_options.py
forgejo_api/models/changed_file.py
forgejo_api/models/combined_status.py
forgejo_api/models/comment.py
forgejo_api/models/commit.py
forgejo_api/models/commit_affected_files.py
forgejo_api/models/commit_date_options.py
forgejo_api/models/commit_meta.py
forgejo_api/models/commit_stats.py
forgejo_api/models/commit_status.py
forgejo_api/models/commit_status_state.py
forgejo_api/models/commit_user.py
forgejo_api/models/contents_response.py
forgejo_api/models/create_access_token_option.py
forgejo_api/models/create_branch_protection_option.py
forgejo_api/models/create_branch_repo_option.py
forgejo_api/models/create_email_option.py
forgejo_api/models/create_file_options.py
forgejo_api/models/create_fork_option.py
forgejo_api/models/create_gpg_key_option.py
forgejo_api/models/create_hook_option.py
forgejo_api/models/create_hook_option_config.py
forgejo_api/models/create_issue_comment_option.py
forgejo_api/models/create_issue_option.py
forgejo_api/models/create_key_option.py
forgejo_api-1.20.1.post1.dist-info/METADATA
forgejo_api-1.20.1.post1.dist-info/WHEEL
forgejo_api-1.20.1.post1.dist-info/top_level.txt
forgejo_api-1.20.1.post1.dist-info/RECORD
